[{"url":"https://www.heavens-above.com/passdetails.aspx?lat=39.9042&lng=116.4074&loc=%e5%8c%97%e4%ba%ac%e5%b8%82&alt=52&tz=ChST&satid=25544&mjd=61055.4115908072&type=A","date":"1月15日","brightness":"-3.6","events":{"rise":{"time":"17:47:17","altitude":"0°","azimuth":"236° (西南)","distance":"2,339","brightness":"2.1","sunAltitude":"-6.7°"},"reachAltitude10deg":{"time":"17:49:22","altitude":"10°","azimuth":"238° (西南偏西)","distance":"1,481","brightness":"0.7","sunAltitude":"-7.1°"},"highestPoint":{"time":"17:52:41","altitude":"72°","azimuth":"324° (西北)","distance":"438","brightness":"-3.6","sunAltitude":"-7.7°"},"dropBelowAltitude10deg":{"time":"17:56:02","altitude":"10°","azimuth":"49° (东北)","distance":"1,491","brightness":"-1.6","sunAltitude":"-8.3°"},"enterShadow":{"time":"17:56:03","altitude":"10°","azimuth":"49° (东北)","distance":"1,499","brightness":"-1.5","sunAltitude":"-8.3°"},"set":{"time":"17:58:08","altitude":"0°","azimuth":"52° (东北)","distance":"2,358","brightness":"-","sunAltitude":"-8.7°"}},"passType":"可见","image":"https://www.heavens-above.com/PassSkyChart2.ashx?passID=683210&size=800&lat=39.9042&lng=116.4074&loc=%e5%8c%97%e4%ba%ac%e5%b8%82&alt=52&tz=ChST&showUnlit=true","scoreData":[17,-3.6,-7.7,72],"exist":401,"score":73,"id":"a0893bfd52329c30525a396ef86407a6"},{"url":"https://www.heavens-above.com/passdetails.aspx?lat=39.9042&lng=116.4074&loc=%e5%8c%97%e4%ba%ac%e5%b8%82&alt=52&tz=ChST&satid=25544&mjd=61052.4440337331&type=A","date":"1月12日","brightness":"-3.8","events":{"rise":{"time":"18:34:01","altitude":"0°","azimuth":"225° (西南)","distance":"2,338","brightness":"1.1","sunAltitude":"-15.8°"},"reachAltitude10deg":{"time":"18:36:06","altitude":"10°","azimuth":"222° (西南)","distance":"1,480","brightness":"-0.1","sunAltitude":"-16.1°"},"highestPoint":{"time":"18:39:24","altitude":"66°","azimuth":"140° (东南)","distance":"457","brightness":"-3.8","sunAltitude":"-16.7°"},"enterShadow":{"time":"18:40:08","altitude":"47°","azimuth":"80° (东)","distance":"556","brightness":"-3.6","sunAltitude":"-16.9°"},"dropBelowAltitude10deg":{"time":"18:42:43","altitude":"10°","azimuth":"58° (东北偏东)","distance":"1,492","brightness":"-","sunAltitude":"-17.4°"},"set":{"time":"18:44:50","altitude":"0°","azimuth":"55° (东北)","distance":"2,360","brightness":"-","sunAltitude":"-17.8°"}},"passType":"可见","image":"https://www.heavens-above.com/PassSkyChart2.ashx?passID=683184&size=800&lat=39.9042&lng=116.4074&loc=%e5%8c%97%e4%ba%ac%e5%b8%82&alt=52&tz=ChST&showUnlit=true","scoreData":[18,-3.8,-16.7,66],"exist":242,"score":73,"id":"0f35ee89021ca986ecc2de65db988199"},{"url":"https://www.heavens-above.com/passdetails.aspx?lat=39.9042&lng=116.4074&loc=%e5%8c%97%e4%ba%ac%e5%b8%82&alt=52&tz=ChST&satid=25544&mjd=61068.4499955836&type=A","date":"1月28日","brightness":"-3.8","events":{"rise":{"time":"18:42:33","altitude":"0°","azimuth":"309° (西北)","distance":"2,355","brightness":"0.7","sunAltitude":"-14.4°"},"reachAltitude10deg":{"time":"18:44:40","altitude":"10°","azimuth":"312° (西北)","distance":"1,490","brightness":"-0.5","sunAltitude":"-14.8°"},"highestPoint":{"time":"18:47:59","altitude":"64°","azimuth":"35° (东北)","distance":"462","brightness":"-3.8","sunAltitude":"-15.4°"},"enterShadow":{"time":"18:49:14","altitude":"34°","azimuth":"106° (东南偏东)","distance":"708","brightness":"-3.1","sunAltitude":"-15.6°"},"dropBelowAltitude10deg":{"time":"18:51:18","altitude":"10°","azimuth":"118° (东南偏东)","distance":"1,485","brightness":"-","sunAltitude":"-16.0°"},"set":{"time":"18:53:24","altitude":"0°","azimuth":"122° (东南偏东)","distance":"2,345","brightness":"-","sunAltitude":"-16.4°"}},"passType":"可见","image":"https://www.heavens-above.com/PassSkyChart2.ashx?passID=683249&size=800&lat=39.9042&lng=116.4074&loc=%e5%8c%97%e4%ba%ac%e5%b8%82&alt=52&tz=ChST&showUnlit=true","scoreData":[18,-3.8,-15.4,64],"exist":274,"score":71,"id":"930c040db0c247aedbcf27c66a121d2a"},{"url":"https://www.heavens-above.com/passdetails.aspx?lat=39.9042&lng=116.4074&loc=%e5%8c%97%e4%ba%ac%e5%b8%82&alt=52&tz=ChST&satid=25544&mjd=61071.4165284153&type=A","date":"1月31日","brightness":"-3.6","events":{"rise":{"time":"17:54:22","altitude":"0°","azimuth":"306° (西北)","distance":"2,353","brightness":"0.6","sunAltitude":"-4.8°"},"reachAltitude10deg":{"time":"17:56:28","altitude":"10°","azimuth":"305° (西北)","distance":"1,488","brightness":"-0.4","sunAltitude":"-5.2°"},"highestPoint":{"time":"17:59:47","altitude":"77°","azimuth":"221° (西南)","distance":"428","brightness":"-3.6","sunAltitude":"-5.8°"},"dropBelowAltitude10deg":{"time":"18:03:07","altitude":"10°","azimuth":"133° (东南)","distance":"1,482","brightness":"-1.3","sunAltitude":"-6.4°"},"set":{"time":"18:05:12","altitude":"0°","azimuth":"132° (东南)","distance":"2,342","brightness":"-0.3","sunAltitude":"-6.8°"}},"passType":"可见","image":"https://www.heavens-above.com/PassSkyChart2.ashx?passID=683220&size=800&lat=39.9042&lng=116.4074&loc=%e5%8c%97%e4%ba%ac%e5%b8%82&alt=52&tz=ChST&showUnlit=true","scoreData":[17,-3.6,-5.8,77],"exist":399,"score":69,"id":"9c0e80c20d685cf2c4355f09c6a33c51"},{"url":"https://www.heavens-above.com/passdetails.aspx?lat=39.9042&lng=116.4074&loc=%e5%8c%97%e4%ba%ac%e5%b8%82&alt=52&tz=ChST&satid=25544&mjd=61054.4448558114&type=A","date":"1月14日","brightness":"-2.9","events":{"rise":{"time":"18:35:14","altitude":"0°","azimuth":"247° (西南偏西)","distance":"2,342","brightness":"1.8","sunAltitude":"-15.6°"},"reachAltitude10deg":{"time":"18:37:23","altitude":"10°","azimuth":"255° (西南偏西)","distance":"1,483","brightness":"0.4","sunAltitude":"-16.0°"},"highestPoint":{"time":"18:40:35","altitude":"43°","azimuth":"328° (西北偏北)","distance":"597","brightness":"-2.9","sunAltitude":"-16.6°"},"enterShadow":{"time":"18:41:49","altitude":"29°","azimuth":"20° (东北偏北)","distance":"797","brightness":"-2.7","sunAltitude":"-16.9°"},"dropBelowAltitude10deg":{"time":"18:43:48","altitude":"10°","azimuth":"42° (东北)","distance":"1,493","brightness":"-","sunAltitude":"-17.2°"},"set":{"time":"18:45:58","altitude":"0°","azimuth":"49° (东北)","distance":"2,360","brightness":"-","sunAltitude":"-17.6°"}},"passType":"可见","image":"https://www.heavens-above.com/PassSkyChart2.ashx?passID=683207&size=800&lat=39.9042&lng=116.4074&loc=%e5%8c%97%e4%ba%ac%e5%b8%82&alt=52&tz=ChST&showUnlit=true","scoreData":[18,-2.9,-16.6,43],"exist":266,"score":69,"id":"3253303d22c4c72d332783b2b9cff794"},{"url":"https://www.heavens-above.com/passdetails.aspx?lat=39.9042&lng=116.4074&loc=%e5%8c%97%e4%ba%ac%e5%b8%82&alt=52&tz=ChST&satid=25544&mjd=61070.4500559432&type=A","date":"1月30日","brightness":"-2.5","events":{"rise":{"time":"18:42:45","altitude":"0°","azimuth":"302° (西北偏西)","distance":"2,353","brightness":"0.8","sunAltitude":"-14.0°"},"reachAltitude10deg":{"time":"18:44:54","altitude":"10°","azimuth":"295° (西北偏西)","distance":"1,488","brightness":"-0.1","sunAltitude":"-14.4°"},"highestPoint":{"time":"18:48:04","altitude":"41°","azimuth":"223° (西南)","distance":"610","brightness":"-2.5","sunAltitude":"-15.0°"},"dropBelowAltitude10deg":{"time":"18:51:14","altitude":"10°","azimuth":"152° (东南偏南)","distance":"1,481","brightness":"-1.2","sunAltitude":"-15.6°"},"enterShadow":{"time":"18:51:40","altitude":"7°","azimuth":"149° (东南偏南)","distance":"1,654","brightness":"-0.9","sunAltitude":"-15.7°"},"set":{"time":"18:53:22","altitude":"0°","azimuth":"144° (东南)","distance":"2,341","brightness":"-","sunAltitude":"-16.0°"}},"passType":"可见","image":"https://www.heavens-above.com/PassSkyChart2.ashx?passID=683247&size=800&lat=39.9042&lng=116.4074&loc=%e5%8c%97%e4%ba%ac%e5%b8%82&alt=52&tz=ChST&showUnlit=true","scoreData":[18,-2.5,-15,41],"exist":406,"score":67,"id":"ed0acaabe1251c0a52f0bced237c2452"},{"url":"https://www.heavens-above.com/passdetails.aspx?lat=39.9042&lng=116.4074&loc=%e5%8c%97%e4%ba%ac%e5%b8%82&alt=52&tz=ChST&satid=25544&mjd=61069.4164285811&type=A","date":"1月29日","brightness":"-3.2","events":{"rise":{"time":"17:54:18","altitude":"0°","azimuth":"311° (西北)","distance":"2,354","brightness":"0.5","sunAltitude":"-5.3°"},"reachAltitude10deg":{"time":"17:56:29","altitude":"10°","azimuth":"320° (西北)","distance":"1,490","brightness":"-0.7","sunAltitude":"-5.6°"},"highestPoint":{"time":"17:59:39","altitude":"39°","azimuth":"31° (东北偏北)","distance":"643","brightness":"-3.2","sunAltitude":"-6.2°"},"dropBelowAltitude10deg":{"time":"18:02:48","altitude":"10°","azimuth":"102° (东南偏东)","distance":"1,485","brightness":"-1.5","sunAltitude":"-6.8°"},"enterShadow":{"time":"18:03:49","altitude":"5°","azimuth":"107° (东南偏东)","distance":"1,880","brightness":"-1.0","sunAltitude":"-7.0°"},"set":{"time":"18:04:59","altitude":"0°","azimuth":"110° (东南偏东)","distance":"2,346","brightness":"-","sunAltitude":"-7.2°"}},"passType":"可见","image":"https://www.heavens-above.com/PassSkyChart2.ashx?passID=683227&size=800&lat=39.9042&lng=116.4074&loc=%e5%8c%97%e4%ba%ac%e5%b8%82&alt=52&tz=ChST&showUnlit=true","scoreData":[17,-3.2,-6.2,39],"exist":440,"score":65,"id":"bd735b5b339c88a1a60d9c4ada96616b"},{"url":"https://www.heavens-above.com/passdetails.aspx?lat=39.9042&lng=116.4074&loc=%e5%8c%97%e4%ba%ac%e5%b8%82&alt=52&tz=ChST&satid=25544&mjd=61053.4109000615&type=A","date":"1月13日","brightness":"-2.9","events":{"rise":{"time":"17:46:27","altitude":"0°","azimuth":"212° (西南偏南)","distance":"2,335","brightness":"1.0","sunAltitude":"-6.9°"},"reachAltitude10deg":{"time":"17:48:37","altitude":"10°","azimuth":"204° (西南偏南)","distance":"1,478","brightness":"-0.3","sunAltitude":"-7.3°"},"highestPoint":{"time":"17:51:41","altitude":"36°","azimuth":"136° (东南)","distance":"679","brightness":"-2.9","sunAltitude":"-7.9°"},"enterShadow":{"time":"17:54:33","altitude":"11°","azimuth":"70° (东北偏东)","distance":"1,403","brightness":"-1.8","sunAltitude":"-8.4°"},"dropBelowAltitude10deg":{"time":"17:54:47","altitude":"10°","azimuth":"68° (东北偏东)","distance":"1,490","brightness":"-","sunAltitude":"-8.4°"},"set":{"time":"17:56:58","altitude":"0°","azimuth":"60° (东北偏东)","distance":"2,357","brightness":"-","sunAltitude":"-8.8°"}},"passType":"可见","image":"https://www.heavens-above.com/PassSkyChart2.ashx?passID=683189&size=800&lat=39.9042&lng=116.4074&loc=%e5%8c%97%e4%ba%ac%e5%b8%82&alt=52&tz=ChST&showUnlit=true","scoreData":[17,-2.9,-7.9,36],"exist":356,"score":65,"id":"bdd2e137232a3ee05818cc4ee00019b6"},{"url":"https://www.heavens-above.com/passdetails.aspx?lat=39.9042&lng=116.4074&loc=%e5%8c%97%e4%ba%ac%e5%b8%82&alt=52&tz=ChST&satid=25544&mjd=61085.908575273&type=A","date":"2月15日","brightness":"-3.9","events":{"rise":{"time":"05:42:56","altitude":"0°","azimuth":"236° (西南偏西)","distance":"2,342","brightness":"-","sunAltitude":"-16.8°"},"reachAltitude10deg":{"time":"05:45:01","altitude":"10°","azimuth":"239° (西南偏西)","distance":"1,482","brightness":"-","sunAltitude":"-16.4°"},"exitShadow":{"time":"05:47:12","altitude":"37°","azimuth":"249° (西南偏西)","distance":"656","brightness":"-3.3","sunAltitude":"-16.0°"},"highestPoint":{"time":"05:48:20","altitude":"71°","azimuth":"323° (西北)","distance":"440","brightness":"-3.9","sunAltitude":"-15.8°"},"dropBelowAltitude10deg":{"time":"05:51:41","altitude":"10°","azimuth":"49° (东北)","distance":"1,489","brightness":"-0.3","sunAltitude":"-15.2°"},"set":{"time":"05:53:47","altitude":"0°","azimuth":"52° (东北)","distance":"2,354","brightness":"0.8","sunAltitude":"-14.8°"}},"passType":"可见","image":"https://www.heavens-above.com/PassSkyChart2.ashx?passID=683298&size=800&lat=39.9042&lng=116.4074&loc=%e5%8c%97%e4%ba%ac%e5%b8%82&alt=52&tz=ChST&showUnlit=true","scoreData":[5,-3.9,-15.8,71],"exist":269,"score":63,"id":"b197d06ec3d0028eba385e85ce8347e4"},{"url":"https://www.heavens-above.com/passdetails.aspx?lat=39.9042&lng=116.4074&loc=%e5%8c%97%e4%ba%ac%e5%b8%82&alt=52&tz=ChST&satid=25544&mjd=61057.4123568233&type=A","date":"1月17日","brightness":"-2.3","events":{"rise":{"time":"17:48:34","altitude":"0°","azimuth":"258° (西南偏西)","distance":"2,344","brightness":"2.3","sunAltitude":"-6.6°"},"reachAltitude10deg":{"time":"17:50:50","altitude":"10°","azimuth":"270° (西)","distance":"1,484","brightness":"0.4","sunAltitude":"-7.0°"},"highestPoint":{"time":"17:53:47","altitude":"29°","azimuth":"332° (西北偏北)","distance":"792","brightness":"-2.3","sunAltitude":"-7.5°"},"dropBelowAltitude10deg":{"time":"17:56:46","altitude":"10°","azimuth":"35° (东北)","distance":"1,492","brightness":"-1.5","sunAltitude":"-8.1°"},"enterShadow":{"time":"17:57:13","altitude":"8°","azimuth":"39° (东北)","distance":"1,657","brightness":"-1.3","sunAltitude":"-8.1°"},"set":{"time":"17:59:03","altitude":"0°","azimuth":"47° (东北)","distance":"2,359","brightness":"-","sunAltitude":"-8.5°"}},"passType":"可见","image":"https://www.heavens-above.com/PassSkyChart2.ashx?passID=683190&size=800&lat=39.9042&lng=116.4074&loc=%e5%8c%97%e4%ba%ac%e5%b8%82&alt=52&tz=ChST&showUnlit=true","scoreData":[17,-2.3,-7.5,29],"exist":383,"score":60,"id":"0614af5bf2998efa16acf0957484fa68"},{"url":"https://www.heavens-above.com/passdetails.aspx?lat=39.9042&lng=116.4074&loc=%e5%8c%97%e4%ba%ac%e5%b8%82&alt=52&tz=ChST&satid=25544&mjd=61056.4457405451&type=A","date":"1月16日","brightness":"-1.8","events":{"rise":{"time":"18:36:48","altitude":"0°","azimuth":"268° (西)","distance":"2,346","brightness":"1.7","sunAltitude":"-15.6°"},"reachAltitude10deg":{"time":"18:39:14","altitude":"10°","azimuth":"285° (西北偏西)","distance":"1,487","brightness":"0.0","sunAltitude":"-16.0°"},"highestPoint":{"time":"18:41:51","altitude":"21°","azimuth":"337° (西北偏北)","distance":"991","brightness":"-1.8","sunAltitude":"-16.5°"},"enterShadow":{"time":"18:43:08","altitude":"17°","azimuth":"9° (北)","distance":"1,130","brightness":"-1.8","sunAltitude":"-16.7°"},"dropBelowAltitude10deg":{"time":"18:44:30","altitude":"10°","azimuth":"29° (东北偏北)","distance":"1,494","brightness":"-","sunAltitude":"-17.0°"},"set":{"time":"18:46:57","altitude":"0°","azimuth":"46° (东北)","distance":"2,360","brightness":"-","sunAltitude":"-17.5°"}},"passType":"可见","image":"https://www.heavens-above.com/PassSkyChart2.ashx?passID=683188&size=800&lat=39.9042&lng=116.4074&loc=%e5%8c%97%e4%ba%ac%e5%b8%82&alt=52&tz=ChST&showUnlit=true","scoreData":[18,-1.8,-16.5,21],"exist":234,"score":57,"id":"a139c5a14de9c6a02908ab6875745a50"},{"url":"https://www.heavens-above.com/passdetails.aspx?lat=39.9042&lng=116.4074&loc=%e5%8c%97%e4%ba%ac%e5%b8%82&alt=52&tz=ChST&satid=25544&mjd=61069.4835179041&type=A","date":"1月29日","brightness":"-1.7","events":{"rise":{"time":"19:31:11","altitude":"0°","azimuth":"296° (西北偏西)","distance":"2,353","brightness":"1.0","sunAltitude":"-23.4°"},"reachAltitude10deg":{"time":"19:33:32","altitude":"10°","azimuth":"282° (西北偏西)","distance":"1,487","brightness":"0.0","sunAltitude":"-23.8°"},"highestPoint":{"time":"19:36:15","altitude":"23°","azimuth":"227° (西南)","distance":"924","brightness":"-1.6","sunAltitude":"-24.4°"},"enterShadow":{"time":"19:36:48","altitude":"22°","azimuth":"211° (西南偏南)","distance":"951","brightness":"-1.7","sunAltitude":"-24.5°"},"dropBelowAltitude10deg":{"time":"19:38:58","altitude":"10°","azimuth":"172° (南)","distance":"1,481","brightness":"-","sunAltitude":"-24.9°"},"set":{"time":"19:41:18","altitude":"0°","azimuth":"158° (东南偏南)","distance":"2,340","brightness":"-","sunAltitude":"-25.3°"}},"passType":"可见","image":"https://www.heavens-above.com/PassSkyChart2.ashx?passID=683218&size=800&lat=39.9042&lng=116.4074&loc=%e5%8c%97%e4%ba%ac%e5%b8%82&alt=52&tz=ChST&showUnlit=true","scoreData":[19,-1.6,-24.4,23],"exist":196,"score":57,"id":"a2555ce0d455d7efe069209cfea49977"},{"url":"https://www.heavens-above.com/passdetails.aspx?lat=39.9042&lng=116.4074&loc=%e5%8c%97%e4%ba%ac%e5%b8%82&alt=52&tz=ChST&satid=25544&mjd=61066.4496950389&type=A","date":"1月26日","brightness":"-2.6","events":{"rise":{"time":"18:42:20","altitude":"0°","azimuth":"313° (西北)","distance":"2,355","brightness":"0.6","sunAltitude":"-14.7°"},"reachAltitude10deg":{"time":"18:44:38","altitude":"10°","azimuth":"326° (西北)","distance":"1,491","brightness":"-0.7","sunAltitude":"-15.1°"},"highestPoint":{"time":"18:47:33","altitude":"27°","azimuth":"27° (东北偏北)","distance":"831","brightness":"-2.6","sunAltitude":"-15.7°"},"enterShadow":{"time":"18:47:44","altitude":"27°","azimuth":"33° (东北偏北)","distance":"834","brightness":"-2.6","sunAltitude":"-15.7°"},"dropBelowAltitude10deg":{"time":"18:50:28","altitude":"10°","azimuth":"88° (东)","distance":"1,488","brightness":"-","sunAltitude":"-16.2°"},"set":{"time":"18:52:45","altitude":"0°","azimuth":"100° (东)","distance":"2,350","brightness":"-","sunAltitude":"-16.7°"}},"passType":"可见","image":"https://www.heavens-above.com/PassSkyChart2.ashx?passID=683214&size=800&lat=39.9042&lng=116.4074&loc=%e5%8c%97%e4%ba%ac%e5%b8%82&alt=52&tz=ChST&showUnlit=true","scoreData":[18,-2.6,-15.7,27],"exist":186,"score":57,"id":"3902881be8828a71a63ad0084d62a77c"},{"url":"https://www.heavens-above.com/passdetails.aspx?lat=39.9042&lng=116.4074&loc=%e5%8c%97%e4%ba%ac%e5%b8%82&alt=52&tz=ChST&satid=25544&mjd=61082.9429824628&type=A","date":"2月12日","brightness":"-3.5","events":{"rise":{"time":"06:32:30","altitude":"0°","azimuth":"226° (西南)","distance":"2,341","brightness":"-0.3","sunAltitude":"-8.1°"},"reachAltitude10deg":{"time":"06:34:35","altitude":"10°","azimuth":"224° (西南)","distance":"1,481","brightness":"-1.3","sunAltitude":"-7.7°"},"highestPoint":{"time":"06:37:53","altitude":"71°","azimuth":"141° (东南)","distance":"440","brightness":"-3.5","sunAltitude":"-7.0°"},"dropBelowAltitude10deg":{"time":"06:41:13","altitude":"10°","azimuth":"56° (东北偏东)","distance":"1,489","brightness":"-0.3","sunAltitude":"-6.4°"},"set":{"time":"06:43:19","altitude":"0°","azimuth":"55° (东北)","distance":"2,354","brightness":"0.7","sunAltitude":"-6.0°"}},"passType":"可见","image":"https://www.heavens-above.com/PassSkyChart2.ashx?passID=683263&size=800&lat=39.9042&lng=116.4074&loc=%e5%8c%97%e4%ba%ac%e5%b8%82&alt=52&tz=ChST&showUnlit=true","scoreData":[6,-3.5,-7,71],"exist":398,"score":55,"id":"756ede4ca76f5c4cefa1aac9f4ead863"},{"url":"https://www.heavens-above.com/passdetails.aspx?lat=39.9042&lng=116.4074&loc=%e5%8c%97%e4%ba%ac%e5%b8%82&alt=52&tz=ChST&satid=25544&mjd=61084.9424812463&type=A","date":"2月14日","brightness":"-3.2","events":{"rise":{"time":"06:31:49","altitude":"0°","azimuth":"248° (西南偏西)","distance":"2,344","brightness":"-","sunAltitude":"-7.7°"},"exitShadow":{"time":"06:33:26","altitude":"7°","azimuth":"253° (西南偏西)","distance":"1,700","brightness":"-1.2","sunAltitude":"-7.4°"},"reachAltitude10deg":{"time":"06:33:59","altitude":"10°","azimuth":"256° (西南偏西)","distance":"1,484","brightness":"-1.5","sunAltitude":"-7.3°"},"highestPoint":{"time":"06:37:10","altitude":"42°","azimuth":"329° (西北偏北)","distance":"608","brightness":"-3.2","sunAltitude":"-6.7°"},"dropBelowAltitude10deg":{"time":"06:40:22","altitude":"10°","azimuth":"41° (东北)","distance":"1,490","brightness":"-0.5","sunAltitude":"-6.1°"},"set":{"time":"06:42:32","altitude":"0°","azimuth":"49° (东北)","distance":"2,355","brightness":"0.6","sunAltitude":"-5.7°"}},"passType":"可见","image":"https://www.heavens-above.com/PassSkyChart2.ashx?passID=683290&size=800&lat=39.9042&lng=116.4074&loc=%e5%8c%97%e4%ba%ac%e5%b8%82&alt=52&tz=ChST&showUnlit=true","scoreData":[6,-3.2,-6.7,42],"exist":416,"score":53,"id":"ac01d89a9657e91823cabefef376a691"},{"url":"https://www.heavens-above.com/passdetails.aspx?lat=39.9042&lng=116.4074&loc=%e5%8c%97%e4%ba%ac%e5%b8%82&alt=52&tz=ChST&satid=25544&mjd=61083.9092032836&type=A","date":"2月13日","brightness":"-2.4","events":{"rise":{"time":"05:43:58","altitude":"0°","azimuth":"214° (西南偏南)","distance":"2,339","brightness":"-","sunAltitude":"-17.1°"},"reachAltitude10deg":{"time":"05:46:08","altitude":"10°","azimuth":"206° (西南偏南)","distance":"1,480","brightness":"-","sunAltitude":"-16.7°"},"exitShadow":{"time":"05:46:27","altitude":"12°","azimuth":"204° (西南偏南)","distance":"1,361","brightness":"-1.4","sunAltitude":"-16.6°"},"highestPoint":{"time":"05:49:14","altitude":"38°","azimuth":"136° (东南)","distance":"651","brightness":"-2.4","sunAltitude":"-16.1°"},"dropBelowAltitude10deg":{"time":"05:52:22","altitude":"10°","azimuth":"67° (东北偏东)","distance":"1,488","brightness":"0.0","sunAltitude":"-15.5°"},"set":{"time":"05:54:33","altitude":"0°","azimuth":"59° (东北偏东)","distance":"2,353","brightness":"1.0","sunAltitude":"-15.0°"}},"passType":"可见","image":"https://www.heavens-above.com/PassSkyChart2.ashx?passID=683306&size=800&lat=39.9042&lng=116.4074&loc=%e5%8c%97%e4%ba%ac%e5%b8%82&alt=52&tz=ChST&showUnlit=true","scoreData":[5,-2.4,-16.1,38],"exist":355,"score":52,"id":"cfa4aa8c9f75aa0c897b35c180253686"},{"url":"https://www.heavens-above.com/passdetails.aspx?lat=39.9042&lng=116.4074&loc=%e5%8c%97%e4%ba%ac%e5%b8%82&alt=52&tz=ChST&satid=25544&mjd=61067.4160955577&type=A","date":"1月27日","brightness":"-2.1","events":{"rise":{"time":"17:54:08","altitude":"0°","azimuth":"314° (西北)","distance":"2,355","brightness":"0.4","sunAltitude":"-5.6°"},"reachAltitude10deg":{"time":"17:56:37","altitude":"10°","azimuth":"332° (西北偏北)","distance":"1,491","brightness":"-0.8","sunAltitude":"-6.1°"},"highestPoint":{"time":"17:59:10","altitude":"20°","azimuth":"22° (东北偏北)","distance":"1,026","brightness":"-2.1","sunAltitude":"-6.5°"},"dropBelowAltitude10deg":{"time":"18:01:44","altitude":"10°","azimuth":"72° (东北偏东)","distance":"1,489","brightness":"-1.7","sunAltitude":"-7.0°"},"enterShadow":{"time":"18:01:56","altitude":"9°","azimuth":"74° (东北偏东)","distance":"1,550","brightness":"-1.6","sunAltitude":"-7.0°"},"set":{"time":"18:04:12","altitude":"0°","azimuth":"90° (东)","distance":"2,351","brightness":"-","sunAltitude":"-7.5°"}},"passType":"可见","image":"https://www.heavens-above.com/PassSkyChart2.ashx?passID=683245&size=800&lat=39.9042&lng=116.4074&loc=%e5%8c%97%e4%ba%ac%e5%b8%82&alt=52&tz=ChST&showUnlit=true","scoreData":[17,-2.1,-6.5,20],"exist":319,"score":51,"id":"9547518791a7923c7b2fca6b282a9986"},{"url":"https://www.heavens-above.com/passdetails.aspx?lat=39.9042&lng=116.4074&loc=%e5%8c%97%e4%ba%ac%e5%b8%82&alt=52&tz=ChST&satid=25544&mjd=61059.4131828704&type=A","date":"1月19日","brightness":"-1.5","events":{"rise":{"time":"17:50:06","altitude":"0°","azimuth":"277° (西)","distance":"2,348","brightness":"1.3","sunAltitude":"-6.5°"},"reachAltitude10deg":{"time":"17:52:44","altitude":"10°","azimuth":"299° (西北偏西)","distance":"1,488","brightness":"-0.4","sunAltitude":"-7.0°"},"highestPoint":{"time":"17:54:59","altitude":"17°","azimuth":"342° (西北偏北)","distance":"1,150","brightness":"-1.5","sunAltitude":"-7.4°"},"dropBelowAltitude10deg":{"time":"17:57:14","altitude":"10°","azimuth":"24° (东北偏北)","distance":"1,492","brightness":"-1.4","sunAltitude":"-7.8°"},"enterShadow":{"time":"17:58:10","altitude":"6°","azimuth":"35° (东北)","distance":"1,771","brightness":"-1.1","sunAltitude":"-7.9°"},"set":{"time":"17:59:53","altitude":"0°","azimuth":"46° (东北)","distance":"2,359","brightness":"-","sunAltitude":"-8.2°"}},"passType":"可见","image":"https://www.heavens-above.com/PassSkyChart2.ashx?passID=683191&size=800&lat=39.9042&lng=116.4074&loc=%e5%8c%97%e4%ba%ac%e5%b8%82&alt=52&tz=ChST&showUnlit=true","scoreData":[17,-1.5,-7.4,17],"exist":326,"score":50,"id":"7aa2bb5a427e839219ad1fba63e5b14e"},{"url":"https://www.heavens-above.com/passdetails.aspx?lat=39.9042&lng=116.4074&loc=%e5%8c%97%e4%ba%ac%e5%b8%82&alt=52&tz=ChST&satid=25544&mjd=61058.4466691351&type=A","date":"1月18日","brightness":"-1.4","events":{"rise":{"time":"18:38:29","altitude":"0°","azimuth":"286° (西北偏西)","distance":"2,350","brightness":"1.1","sunAltitude":"-15.5°"},"reachAltitude10deg":{"time":"18:41:23","altitude":"10°","azimuth":"314° (西北)","distance":"1,490","brightness":"-0.5","sunAltitude":"-16.1°"},"highestPoint":{"time":"18:43:12","altitude":"14°","azimuth":"347° (西北偏北)","distance":"1,284","brightness":"-1.3","sunAltitude":"-16.4°"},"enterShadow":{"time":"18:44:11","altitude":"12°","azimuth":"6° (北)","distance":"1,350","brightness":"-1.4","sunAltitude":"-16.6°"},"dropBelowAltitude10deg":{"time":"18:45:01","altitude":"10°","azimuth":"20° (东北偏北)","distance":"1,494","brightness":"-","sunAltitude":"-16.7°"},"set":{"time":"18:47:56","altitude":"0°","azimuth":"48° (东北)","distance":"2,360","brightness":"-","sunAltitude":"-17.3°"}},"passType":"可见","image":"https://www.heavens-above.com/PassSkyChart2.ashx?passID=683192&size=800&lat=39.9042&lng=116.4074&loc=%e5%8c%97%e4%ba%ac%e5%b8%82&alt=52&tz=ChST&showUnlit=true","scoreData":[18,-1.3,-16.4,14],"exist":168,"score":48,"id":"db679260e9d516dc292581de7ca83ad1"},{"url":"https://www.heavens-above.com/passdetails.aspx?lat=39.9042&lng=116.4074&loc=%e5%8c%97%e4%ba%ac%e5%b8%82&alt=52&tz=ChST&satid=25544&mjd=61065.4155528953&type=A","date":"1月25日","brightness":"-1.6","events":{"rise":{"time":"17:53:42","altitude":"0°","azimuth":"312° (西北)","distance":"2,355","brightness":"0.5","sunAltitude":"-6.0°"},"reachAltitude10deg":{"time":"17:56:39","altitude":"10°","azimuth":"341° (西北偏北)","distance":"1,491","brightness":"-0.9","sunAltitude":"-6.5°"},"highestPoint":{"time":"17:58:23","altitude":"13°","azimuth":"12° (东北偏北)","distance":"1,302","brightness":"-1.6","sunAltitude":"-6.8°"},"dropBelowAltitude10deg":{"time":"18:00:07","altitude":"10°","azimuth":"43° (东北)","distance":"1,491","brightness":"-1.5","sunAltitude":"-7.1°"},"enterShadow":{"time":"18:00:42","altitude":"8°","azimuth":"51° (东北)","distance":"1,623","brightness":"-1.4","sunAltitude":"-7.2°"},"set":{"time":"18:03:05","altitude":"0°","azimuth":"72° (东北偏东)","distance":"2,354","brightness":"-","sunAltitude":"-7.7°"}},"passType":"可见","image":"https://www.heavens-above.com/PassSkyChart2.ashx?passID=683213&size=800&lat=39.9042&lng=116.4074&loc=%e5%8c%97%e4%ba%ac%e5%b8%82&alt=52&tz=ChST&showUnlit=true","scoreData":[17,-1.6,-6.8,13],"exist":243,"score":46,"id":"5245b59f6f89768dbc62b78efa0e9eeb"},{"url":"https://www.heavens-above.com/passdetails.aspx?lat=39.9042&lng=116.4074&loc=%e5%8c%97%e4%ba%ac%e5%b8%82&alt=52&tz=ChST&satid=25544&mjd=61087.9080107957&type=A","date":"2月17日","brightness":"-2.7","events":{"rise":{"time":"05:42:18","altitude":"0°","azimuth":"257° (西南偏西)","distance":"2,346","brightness":"-","sunAltitude":"-16.5°"},"reachAltitude10deg":{"time":"05:44:33","altitude":"10°","azimuth":"269° (西)","distance":"1,485","brightness":"-","sunAltitude":"-16.1°"},"exitShadow":{"time":"05:47:03","altitude":"28°","azimuth":"315° (西北)","distance":"806","brightness":"-2.7","sunAltitude":"-15.6°"},"highestPoint":{"time":"05:47:32","altitude":"30°","azimuth":"332° (西北偏北)","distance":"781","brightness":"-2.7","sunAltitude":"-15.5°"},"dropBelowAltitude10deg":{"time":"05:50:31","altitude":"10°","azimuth":"36° (东北)","distance":"1,490","brightness":"-0.5","sunAltitude":"-14.9°"},"set":{"time":"05:52:47","altitude":"0°","azimuth":"47° (东北)","distance":"2,355","brightness":"0.7","sunAltitude":"-14.5°"}},"passType":"可见","image":"https://www.heavens-above.com/PassSkyChart2.ashx?passID=683277&size=800&lat=39.9042&lng=116.4074&loc=%e5%8c%97%e4%ba%ac%e5%b8%82&alt=52&tz=ChST&showUnlit=true","scoreData":[5,-2.7,-15.5,30],"exist":208,"score":46,"id":"548194390e7ffbe12938dcb1426d9cf3"},{"url":"https://www.heavens-above.com/passdetails.aspx?lat=39.9042&lng=116.4074&loc=%e5%8c%97%e4%ba%ac%e5%b8%82&alt=52&tz=ChST&satid=25544&mjd=61072.4498824336&type=A","date":"2月1日","brightness":"-0.6","events":{"rise":{"time":"18:43:09","altitude":"0°","azimuth":"290° (西北偏西)","distance":"2,351","brightness":"1.1","sunAltitude":"-13.7°"},"reachAltitude10deg":{"time":"18:45:57","altitude":"10°","azimuth":"265° (西)","distance":"1,485","brightness":"0.5","sunAltitude":"-14.2°"},"highestPoint":{"time":"18:47:49","altitude":"14°","azimuth":"230° (西南)","distance":"1,248","brightness":"-0.5","sunAltitude":"-14.6°"},"dropBelowAltitude10deg":{"time":"18:49:41","altitude":"10°","azimuth":"196° (西南偏南)","distance":"1,480","brightness":"-0.7","sunAltitude":"-14.9°"},"set":{"time":"18:52:28","altitude":"0°","azimuth":"170° (南)","distance":"2,338","brightness":"0.0","sunAltitude":"-15.4°"}},"passType":"可见","image":"https://www.heavens-above.com/PassSkyChart2.ashx?passID=683242&size=800&lat=39.9042&lng=116.4074&loc=%e5%8c%97%e4%ba%ac%e5%b8%82&alt=52&tz=ChST&showUnlit=true","scoreData":[18,-0.5,-14.6,14],"exist":224,"score":44,"id":"27bada6b9537660c776f0300b9beb64a"},{"url":"https://www.heavens-above.com/passdetails.aspx?lat=39.9042&lng=116.4074&loc=%e5%8c%97%e4%ba%ac%e5%b8%82&alt=52&tz=ChST&satid=25544&mjd=61061.4140276788&type=A","date":"1月21日","brightness":"-1.3","events":{"rise":{"time":"17:51:37","altitude":"0°","azimuth":"294° (西北偏西)","distance":"2,351","brightness":"0.8","sunAltitude":"-6.4°"},"reachAltitude10deg":{"time":"17:54:47","altitude":"10°","azimuth":"327° (西北偏北)","distance":"1,491","brightness":"-0.8","sunAltitude":"-6.9°"},"highestPoint":{"time":"17:56:12","altitude":"12°","azimuth":"352° (北)","distance":"1,369","brightness":"-1.3","sunAltitude":"-7.2°"},"dropBelowAltitude10deg":{"time":"17:57:36","altitude":"10°","azimuth":"17° (东北偏北)","distance":"1,492","brightness":"-1.3","sunAltitude":"-7.5°"},"enterShadow":{"time":"17:59:00","altitude":"6°","azimuth":"35° (东北)","distance":"1,802","brightness":"-1.0","sunAltitude":"-7.7°"},"set":{"time":"18:00:47","altitude":"0°","azimuth":"50° (东北)","distance":"2,358","brightness":"-","sunAltitude":"-8.0°"}},"passType":"可见","image":"https://www.heavens-above.com/PassSkyChart2.ashx?passID=683197&size=800&lat=39.9042&lng=116.4074&loc=%e5%8c%97%e4%ba%ac%e5%b8%82&alt=52&tz=ChST&showUnlit=true","scoreData":[17,-1.3,-7.2,12],"exist":253,"score":42,"id":"9e677a05c8f8b11c89aab295a57f0733"},{"url":"https://www.heavens-above.com/passdetails.aspx?lat=39.9042&lng=116.4074&loc=%e5%8c%97%e4%ba%ac%e5%b8%82&alt=52&tz=ChST&satid=25544&mjd=61084.8754452597&type=A","date":"2月14日","brightness":"-1.5","events":{"rise":{"time":"04:55:39","altitude":"0°","azimuth":"200° (西南偏南)","distance":"2,337","brightness":"-","sunAltitude":"-26.1°"},"reachAltitude10deg":{"time":"04:58:02","altitude":"10°","azimuth":"184° (南)","distance":"1,479","brightness":"-","sunAltitude":"-25.7°"},"exitShadow":{"time":"05:00:30","altitude":"21°","azimuth":"136° (东南)","distance":"984","brightness":"-1.5","sunAltitude":"-25.2°"},"highestPoint":{"time":"05:00:38","altitude":"21°","azimuth":"132° (东南)","distance":"982","brightness":"-1.5","sunAltitude":"-25.2°"},"dropBelowAltitude10deg":{"time":"05:03:14","altitude":"10°","azimuth":"81° (东)","distance":"1,486","brightness":"0.1","sunAltitude":"-24.7°"},"set":{"time":"05:05:38","altitude":"0°","azimuth":"65° (东北偏东)","distance":"2,353","brightness":"1.2","sunAltitude":"-24.2°"}},"passType":"可见","image":"https://www.heavens-above.com/PassSkyChart2.ashx?passID=683265&size=800&lat=39.9042&lng=116.4074&loc=%e5%8c%97%e4%ba%ac%e5%b8%82&alt=52&tz=ChST&showUnlit=true","scoreData":[5,-1.5,-25.2,21],"exist":164,"score":41,"id":"f2c296401118c5ed6c0d581b3668ea6c"},{"url":"https://www.heavens-above.com/passdetails.aspx?lat=39.9042&lng=116.4074&loc=%e5%8c%97%e4%ba%ac%e5%b8%82&alt=52&tz=ChST&satid=25544&mjd=61086.9420356532&type=A","date":"2月16日","brightness":"-2.2","events":{"rise":{"time":"06:31:28","altitude":"0°","azimuth":"268° (西)","distance":"2,348","brightness":"-","sunAltitude":"-7.4°"},"exitShadow":{"time":"06:33:40","altitude":"9°","azimuth":"283° (西北偏西)","distance":"1,557","brightness":"-1.6","sunAltitude":"-6.9°"},"reachAltitude10deg":{"time":"06:33:53","altitude":"10°","azimuth":"285° (西北偏西)","distance":"1,487","brightness":"-1.7","sunAltitude":"-6.9°"},"highestPoint":{"time":"06:36:31","altitude":"21°","azimuth":"337° (西北偏北)","distance":"987","brightness":"-2.2","sunAltitude":"-6.4°"},"dropBelowAltitude10deg":{"time":"06:39:10","altitude":"10°","azimuth":"29° (东北偏北)","distance":"1,490","brightness":"-0.7","sunAltitude":"-5.9°"},"set":{"time":"06:41:36","altitude":"0°","azimuth":"46° (东北)","distance":"2,355","brightness":"0.6","sunAltitude":"-5.5°"}},"passType":"可见","image":"https://www.heavens-above.com/PassSkyChart2.ashx?passID=683266&size=800&lat=39.9042&lng=116.4074&loc=%e5%8c%97%e4%ba%ac%e5%b8%82&alt=52&tz=ChST&showUnlit=true","scoreData":[6,-2.2,-6.4,21],"exist":330,"score":39,"id":"5c34f12329af1cbf7352661abdad4b7a"},{"url":"https://www.heavens-above.com/passdetails.aspx?lat=39.9042&lng=116.4074&loc=%e5%8c%97%e4%ba%ac%e5%b8%82&alt=52&tz=ChST&satid=25544&mjd=61060.4475952676&type=A","date":"1月20日","brightness":"-1.2","events":{"rise":{"time":"18:40:01","altitude":"0°","azimuth":"301° (西北偏西)","distance":"2,353","brightness":"0.8","sunAltitude":"-15.4°"},"reachAltitude10deg":{"time":"18:43:25","altitude":"10°","azimuth":"338° (西北偏北)","distance":"1,492","brightness":"-0.9","sunAltitude":"-16.1°"},"highestPoint":{"time":"18:44:32","altitude":"11°","azimuth":"357° (北)","distance":"1,418","brightness":"-1.2","sunAltitude":"-16.3°"},"enterShadow":{"time":"18:45:04","altitude":"11°","azimuth":"7° (北)","distance":"1,436","brightness":"-1.2","sunAltitude":"-16.4°"},"dropBelowAltitude10deg":{"time":"18:45:38","altitude":"10°","azimuth":"17° (东北偏北)","distance":"1,493","brightness":"-","sunAltitude":"-16.5°"},"set":{"time":"18:49:03","altitude":"0°","azimuth":"54° (东北)","distance":"2,359","brightness":"-","sunAltitude":"-17.1°"}},"passType":"可见","image":"https://www.heavens-above.com/PassSkyChart2.ashx?passID=683198&size=800&lat=39.9042&lng=116.4074&loc=%e5%8c%97%e4%ba%ac%e5%b8%82&alt=52&tz=ChST&showUnlit=true","scoreData":[18,-1.2,-16.3,11],"exist":99,"score":39,"id":"735e717fa34e76e302d6dba9b571de7a"},{"url":"https://www.heavens-above.com/passdetails.aspx?lat=39.9042&lng=116.4074&loc=%e5%8c%97%e4%ba%ac%e5%b8%82&alt=52&tz=ChST&satid=25544&mjd=61051.4102720212&type=A","date":"1月11日","brightness":"-1.5","events":{"rise":{"time":"17:46:19","altitude":"0°","azimuth":"185° (南)","distance":"2,334","brightness":"0.4","sunAltitude":"-7.3°"},"reachAltitude10deg":{"time":"17:49:25","altitude":"10°","azimuth":"153° (东南偏南)","distance":"1,479","brightness":"-1.0","sunAltitude":"-7.8°"},"highestPoint":{"time":"17:50:47","altitude":"12°","azimuth":"129° (东南)","distance":"1,362","brightness":"-1.4","sunAltitude":"-8.1°"},"dropBelowAltitude10deg":{"time":"17:52:09","altitude":"10°","azimuth":"104° (东南偏东)","distance":"1,485","brightness":"-1.5","sunAltitude":"-8.3°"},"enterShadow":{"time":"17:52:40","altitude":"9°","azimuth":"97° (东)","distance":"1,584","brightness":"-1.4","sunAltitude":"-8.4°"},"set":{"time":"17:55:17","altitude":"0°","azimuth":"72° (东北偏东)","distance":"2,355","brightness":"-","sunAltitude":"-8.9°"}},"passType":"可见","image":"https://www.heavens-above.com/PassSkyChart2.ashx?passID=683176&size=800&lat=39.9042&lng=116.4074&loc=%e5%8c%97%e4%ba%ac%e5%b8%82&alt=52&tz=ChST&showUnlit=true","scoreData":[17,-1.4,-8.1,12],"exist":195,"score":38,"id":"f1348d7e5893fe6d2c08ff55d22cfa6f"},{"url":"https://www.heavens-above.com/passdetails.aspx?lat=39.9042&lng=116.4074&loc=%e5%8c%97%e4%ba%ac%e5%b8%82&alt=52&tz=ChST&satid=25544&mjd=61062.4484555959&type=A","date":"1月22日","brightness":"-1.4","events":{"rise":{"time":"18:41:11","altitude":"0°","azimuth":"310° (西北)","distance":"2,355","brightness":"0.6","sunAltitude":"-15.3°"},"reachAltitude10deg":{"time":"18:44:24","altitude":"10°","azimuth":"343° (西北偏北)","distance":"1,492","brightness":"-0.9","sunAltitude":"-15.9°"},"highestPoint":{"time":"18:45:46","altitude":"12°","azimuth":"7° (北)","distance":"1,380","brightness":"-1.3","sunAltitude":"-16.1°"},"enterShadow":{"time":"18:45:51","altitude":"12°","azimuth":"9° (北)","distance":"1,381","brightness":"-1.4","sunAltitude":"-16.1°"},"dropBelowAltitude10deg":{"time":"18:47:07","altitude":"10°","azimuth":"31° (东北偏北)","distance":"1,493","brightness":"-","sunAltitude":"-16.4°"},"set":{"time":"18:50:20","altitude":"0°","azimuth":"65° (东北偏东)","distance":"2,357","brightness":"-","sunAltitude":"-17.0°"}},"passType":"可见","image":"https://www.heavens-above.com/PassSkyChart2.ashx?passID=683202&size=800&lat=39.9042&lng=116.4074&loc=%e5%8c%97%e4%ba%ac%e5%b8%82&alt=52&tz=ChST&showUnlit=true","scoreData":[18,-1.3,-16.1,12],"exist":87,"score":37,"id":"5b4c9d14c27c90412a072a6366d1788a"},{"url":"https://www.heavens-above.com/passdetails.aspx?lat=39.9042&lng=116.4074&loc=%e5%8c%97%e4%ba%ac%e5%b8%82&alt=52&tz=ChST&satid=25544&mjd=61080.9435447842&type=A","date":"2月10日","brightness":"-1.2","events":{"rise":{"time":"06:33:39","altitude":"0°","azimuth":"202° (西南偏南)","distance":"2,338","brightness":"-0.1","sunAltitude":"-8.2°"},"reachAltitude10deg":{"time":"06:35:59","altitude":"10°","azimuth":"188° (南)","distance":"1,479","brightness":"-0.9","sunAltitude":"-7.8°"},"highestPoint":{"time":"06:38:42","altitude":"23°","azimuth":"133° (东南)","distance":"918","brightness":"-1.2","sunAltitude":"-7.3°"},"dropBelowAltitude10deg":{"time":"06:41:25","altitude":"10°","azimuth":"78° (东北偏东)","distance":"1,487","brightness":"0.2","sunAltitude":"-6.8°"},"set":{"time":"06:43:46","altitude":"0°","azimuth":"64° (东北偏东)","distance":"2,352","brightness":"0.9","sunAltitude":"-6.4°"}},"passType":"可见","image":"https://www.heavens-above.com/PassSkyChart2.ashx?passID=683254&size=800&lat=39.9042&lng=116.4074&loc=%e5%8c%97%e4%ba%ac%e5%b8%82&alt=52&tz=ChST&showUnlit=true","scoreData":[6,-1.2,-7.3,23],"exist":326,"score":36,"id":"324abc8e010d7fcef7373300e73a302d"},{"url":"https://www.heavens-above.com/passdetails.aspx?lat=39.9042&lng=116.4074&loc=%e5%8c%97%e4%ba%ac%e5%b8%82&alt=52&tz=ChST&satid=25544&mjd=61063.4148449509&type=A","date":"1月23日","brightness":"-1.3","events":{"rise":{"time":"17:52:52","altitude":"0°","azimuth":"306° (西北)","distance":"2,354","brightness":"0.6","sunAltitude":"-6.2°"},"reachAltitude10deg":{"time":"17:56:17","altitude":"10°","azimuth":"343° (西北偏北)","distance":"1,492","brightness":"-1.0","sunAltitude":"-6.8°"},"highestPoint":{"time":"17:57:22","altitude":"11°","azimuth":"2° (北)","distance":"1,422","brightness":"-1.3","sunAltitude":"-7.0°"},"dropBelowAltitude10deg":{"time":"17:58:27","altitude":"10°","azimuth":"21° (东北偏北)","distance":"1,492","brightness":"-1.3","sunAltitude":"-7.2°"},"enterShadow":{"time":"17:59:47","altitude":"6°","azimuth":"40° (东北)","distance":"1,745","brightness":"-1.1","sunAltitude":"-7.5°"},"set":{"time":"18:01:52","altitude":"0°","azimuth":"58° (东北偏东)","distance":"2,357","brightness":"-","sunAltitude":"-7.8°"}},"passType":"可见","image":"https://www.heavens-above.com/PassSkyChart2.ashx?passID=683224&size=800&lat=39.9042&lng=116.4074&loc=%e5%8c%97%e4%ba%ac%e5%b8%82&alt=52&tz=ChST&showUnlit=true","scoreData":[17,-1.3,-7,11],"exist":210,"score":35,"id":"86d5089b73a63a2a3d8466c19aee2021"},{"url":"https://www.heavens-above.com/passdetails.aspx?lat=39.9042&lng=116.4074&loc=%e5%8c%97%e4%ba%ac%e5%b8%82&alt=52&tz=ChST&satid=25544&mjd=61089.9074943739&type=A","date":"2月19日","brightness":"-1.9","events":{"rise":{"time":"05:41:52","altitude":"0°","azimuth":"276° (西)","distance":"2,349","brightness":"-","sunAltitude":"-16.1°"},"reachAltitude10deg":{"time":"05:44:28","altitude":"10°","azimuth":"297° (西北偏西)","distance":"1,488","brightness":"-","sunAltitude":"-15.6°"},"exitShadow":{"time":"05:46:19","altitude":"17°","azimuth":"331° (西北偏北)","distance":"1,146","brightness":"-1.9","sunAltitude":"-15.3°"},"highestPoint":{"time":"05:46:46","altitude":"17°","azimuth":"341° (西北偏北)","distance":"1,130","brightness":"-1.8","sunAltitude":"-15.2°"},"dropBelowAltitude10deg":{"time":"05:49:05","altitude":"10°","azimuth":"25° (东北偏北)","distance":"1,490","brightness":"-0.7","sunAltitude":"-14.7°"},"set":{"time":"05:51:42","altitude":"0°","azimuth":"46° (东北)","distance":"2,355","brightness":"0.7","sunAltitude":"-14.2°"}},"passType":"可见","image":"https://www.heavens-above.com/PassSkyChart2.ashx?passID=683267&size=800&lat=39.9042&lng=116.4074&loc=%e5%8c%97%e4%ba%ac%e5%b8%82&alt=52&tz=ChST&showUnlit=true","scoreData":[5,-1.8,-15.2,17],"exist":166,"score":35,"id":"e39aa9f58fa6d46f3e254148f25b6fdc"},{"url":"https://www.heavens-above.com/passdetails.aspx?lat=39.9042&lng=116.4074&loc=%e5%8c%97%e4%ba%ac%e5%b8%82&alt=52&tz=ChST&satid=25544&mjd=61088.9416233239&type=A","date":"2月18日","brightness":"-1.5","events":{"rise":{"time":"06:31:12","altitude":"0°","azimuth":"286° (西北偏西)","distance":"2,351","brightness":"-","sunAltitude":"-6.9°"},"exitShadow":{"time":"06:33:11","altitude":"7°","azimuth":"302° (西北偏西)","distance":"1,714","brightness":"-1.2","sunAltitude":"-6.6°"},"reachAltitude10deg":{"time":"06:34:05","altitude":"10°","azimuth":"313° (西北)","distance":"1,489","brightness":"-1.5","sunAltitude":"-6.4°"},"highestPoint":{"time":"06:35:55","altitude":"14°","azimuth":"347° (西北偏北)","distance":"1,273","brightness":"-1.5","sunAltitude":"-6.1°"},"dropBelowAltitude10deg":{"time":"06:37:46","altitude":"10°","azimuth":"20° (东北偏北)","distance":"1,491","brightness":"-0.8","sunAltitude":"-5.7°"},"set":{"time":"06:40:39","altitude":"0°","azimuth":"47° (东北)","distance":"2,354","brightness":"0.6","sunAltitude":"-5.2°"}},"passType":"可见","image":"https://www.heavens-above.com/PassSkyChart2.ashx?passID=683271&size=800&lat=39.9042&lng=116.4074&loc=%e5%8c%97%e4%ba%ac%e5%b8%82&alt=52&tz=ChST&showUnlit=true","scoreData":[6,-1.5,-6.1,14],"exist":275,"score":31,"id":"bfe51fca9b33e18815c6cf1fe8f49af1"},{"url":"https://www.heavens-above.com/passdetails.aspx?lat=39.9042&lng=116.4074&loc=%e5%8c%97%e4%ba%ac%e5%b8%82&alt=52&tz=ChST&satid=25544&mjd=61081.9098796868&type=A","date":"2月11日","brightness":"-0.7","events":{"rise":{"time":"05:45:38","altitude":"0°","azimuth":"188° (南)","distance":"2,337","brightness":"0.0","sunAltitude":"-17.2°"},"reachAltitude10deg":{"time":"05:48:32","altitude":"10°","azimuth":"160° (东南偏南)","distance":"1,480","brightness":"-0.7","sunAltitude":"-16.6°"},"highestPoint":{"time":"05:50:13","altitude":"13°","azimuth":"129° (东南)","distance":"1,295","brightness":"-0.5","sunAltitude":"-16.3°"},"dropBelowAltitude10deg":{"time":"05:51:55","altitude":"10°","azimuth":"99° (东)","distance":"1,485","brightness":"0.4","sunAltitude":"-16.0°"},"set":{"time":"05:54:49","altitude":"0°","azimuth":"71° (东北偏东)","distance":"2,351","brightness":"1.3","sunAltitude":"-15.4°"}},"passType":"可见","image":"https://www.heavens-above.com/PassSkyChart2.ashx?passID=683259&size=800&lat=39.9042&lng=116.4074&loc=%e5%8c%97%e4%ba%ac%e5%b8%82&alt=52&tz=ChST&showUnlit=true","scoreData":[5,-0.5,-16.3,13],"exist":203,"score":29,"id":"f7ae8a61a8e07a9a4fa13dd26824d293"},{"url":"https://www.heavens-above.com/passdetails.aspx?lat=39.9042&lng=116.4074&loc=%e5%8c%97%e4%ba%ac%e5%b8%82&alt=52&tz=ChST&satid=25544&mjd=61091.9069829171&type=A","date":"2月21日","brightness":"-1.4","events":{"rise":{"time":"05:41:27","altitude":"0°","azimuth":"292° (西北偏西)","distance":"2,352","brightness":"-","sunAltitude":"-15.7°"},"reachAltitude10deg":{"time":"05:44:34","altitude":"10°","azimuth":"324° (西北)","distance":"1,490","brightness":"-","sunAltitude":"-15.1°"},"exitShadow":{"time":"05:45:12","altitude":"12°","azimuth":"335° (西北偏北)","distance":"1,400","brightness":"-1.4","sunAltitude":"-15.0°"},"highestPoint":{"time":"05:46:03","altitude":"12°","azimuth":"351° (北)","distance":"1,354","brightness":"-1.3","sunAltitude":"-14.8°"},"dropBelowAltitude10deg":{"time":"05:47:32","altitude":"10°","azimuth":"17° (东北偏北)","distance":"1,490","brightness":"-0.8","sunAltitude":"-14.6°"},"set":{"time":"05:50:40","altitude":"0°","azimuth":"49° (东北)","distance":"2,354","brightness":"0.8","sunAltitude":"-14.0°"}},"passType":"可见","image":"https://www.heavens-above.com/PassSkyChart2.ashx?passID=683269&size=800&lat=39.9042&lng=116.4074&loc=%e5%8c%97%e4%ba%ac%e5%b8%82&alt=52&tz=ChST&showUnlit=true","scoreData":[5,-1.3,-14.8,12],"exist":140,"score":26,"id":"9aaf9d5a31abae0a1d5b58031a5a01f6"},{"url":"https://www.heavens-above.com/passdetails.aspx?lat=39.9042&lng=116.4074&loc=%e5%8c%97%e4%ba%ac%e5%b8%82&alt=52&tz=ChST&satid=25544&mjd=61042.9114830841&type=A","date":"1月3日","brightness":"-2.6","events":{"rise":{"time":"05:46:46","altitude":"0°","azimuth":"300° (西北偏西)","distance":"2,377","brightness":"-","sunAltitude":"-20.3°"},"reachAltitude10deg":{"time":"05:48:59","altitude":"10°","azimuth":"291° (西北偏西)","distance":"1,510","brightness":"-","sunAltitude":"-19.9°"},"highestPoint":{"time":"05:52:04","altitude":"33°","azimuth":"225° (西南)","distance":"727","brightness":"-","sunAltitude":"-19.3°"},"exitShadow":{"time":"05:52:32","altitude":"32°","azimuth":"206° (西南偏南)","distance":"753","brightness":"-2.6","sunAltitude":"-19.2°"},"dropBelowAltitude10deg":{"time":"05:55:09","altitude":"10°","azimuth":"159° (东南偏南)","distance":"1,503","brightness":"-0.5","sunAltitude":"-18.7°"},"set":{"time":"05:57:21","altitude":"0°","azimuth":"149° (东南偏南)","distance":"2,364","brightness":"0.8","sunAltitude":"-18.3°"}},"passType":"可见","image":"https://www.heavens-above.com/PassSkyChart2.ashx?passID=683170&size=800&lat=39.9042&lng=116.4074&loc=%e5%8c%97%e4%ba%ac%e5%b8%82&alt=52&tz=ChST&showUnlit=true","scoreData":[5,null,-19.3,33],"exist":157,"score":0,"id":"358c4f82daa912a25f7b538ef8c97250"},{"url":"https://www.heavens-above.com/passdetails.aspx?lat=39.9042&lng=116.4074&loc=%e5%8c%97%e4%ba%ac%e5%b8%82&alt=52&tz=ChST&satid=25544&mjd=61050.4430946904&type=A","date":"1月10日","brightness":"-2.1","events":{"rise":{"time":"18:33:21","altitude":"0°","azimuth":"200° (西南偏南)","distance":"2,335","brightness":"0.5","sunAltitude":"-16.0°"},"reachAltitude10deg":{"time":"18:35:45","altitude":"10°","azimuth":"183° (南)","distance":"1,478","brightness":"-0.8","sunAltitude":"-16.4°"},"enterShadow":{"time":"18:38:03","altitude":"21°","azimuth":"140° (东南)","distance":"998","brightness":"-2.1","sunAltitude":"-16.8°"},"highestPoint":{"time":"18:38:20","altitude":"21°","azimuth":"132° (东南)","distance":"992","brightness":"-","sunAltitude":"-16.9°"},"dropBelowAltitude10deg":{"time":"18:40:55","altitude":"10°","azimuth":"81° (东)","distance":"1,489","brightness":"-","sunAltitude":"-17.4°"},"set":{"time":"18:43:20","altitude":"0°","azimuth":"65° (东北偏东)","distance":"2,358","brightness":"-","sunAltitude":"-17.8°"}},"passType":"可见","image":"https://www.heavens-above.com/PassSkyChart2.ashx?passID=683181&size=800&lat=39.9042&lng=116.4074&loc=%e5%8c%97%e4%ba%ac%e5%b8%82&alt=52&tz=ChST&showUnlit=true","scoreData":[18,null,-16.9,21],"exist":138,"score":0,"id":"53eb2001e9f861a7446de82d924004ca"},{"url":"https://www.heavens-above.com/passdetails.aspx?lat=39.9042&lng=116.4074&loc=%e5%8c%97%e4%ba%ac%e5%b8%82&alt=52&tz=ChST&satid=25544&mjd=61086.8755343567&type=A","date":"2月16日","brightness":"-2.2","events":{"rise":{"time":"04:54:10","altitude":"0°","azimuth":"224° (西南)","distance":"2,340","brightness":"-","sunAltitude":"-26.0°"},"reachAltitude10deg":{"time":"04:56:16","altitude":"10°","azimuth":"221° (西南)","distance":"1,481","brightness":"-","sunAltitude":"-25.6°"},"highestPoint":{"time":"04:59:33","altitude":"63°","azimuth":"140° (东南)","distance":"465","brightness":"-","sunAltitude":"-24.9°"},"exitShadow":{"time":"05:00:46","altitude":"34°","azimuth":"71° (东北偏东)","distance":"698","brightness":"-2.2","sunAltitude":"-24.7°"},"dropBelowAltitude10deg":{"time":"05:02:52","altitude":"10°","azimuth":"58° (东北偏东)","distance":"1,489","brightness":"-0.2","sunAltitude":"-24.3°"},"set":{"time":"05:04:58","altitude":"0°","azimuth":"55° (东北)","distance":"2,354","brightness":"1.0","sunAltitude":"-23.9°"}},"passType":"可见","image":"https://www.heavens-above.com/PassSkyChart2.ashx?passID=683302&size=800&lat=39.9042&lng=116.4074&loc=%e5%8c%97%e4%ba%ac%e5%b8%82&alt=52&tz=ChST&showUnlit=true","scoreData":[4,null,-24.9,63],"exist":126,"score":0,"id":"58f85abdc80a412ea018d15d295c21b5"},{"url":"https://www.heavens-above.com/passdetails.aspx?lat=39.9042&lng=116.4074&loc=%e5%8c%97%e4%ba%ac%e5%b8%82&alt=52&tz=ChST&satid=25544&mjd=61064.4490901951&type=A","date":"1月24日","brightness":"-1.8","events":{"rise":{"time":"18:41:56","altitude":"0°","azimuth":"313° (西北)","distance":"2,355","brightness":"0.5","sunAltitude":"-15.0°"},"reachAltitude10deg":{"time":"18:44:37","altitude":"10°","azimuth":"336° (西北偏北)","distance":"1,492","brightness":"-0.8","sunAltitude":"-15.5°"},"enterShadow":{"time":"18:46:41","altitude":"16°","azimuth":"15° (东北偏北)","distance":"1,176","brightness":"-1.8","sunAltitude":"-15.9°"},"highestPoint":{"time":"18:46:48","altitude":"16°","azimuth":"17° (东北偏北)","distance":"1,175","brightness":"-","sunAltitude":"-15.9°"},"dropBelowAltitude10deg":{"time":"18:48:59","altitude":"10°","azimuth":"58° (东北偏东)","distance":"1,491","brightness":"-","sunAltitude":"-16.3°"},"set":{"time":"18:51:39","altitude":"0°","azimuth":"81° (东)","distance":"2,354","brightness":"-","sunAltitude":"-16.9°"}},"passType":"可见","image":"https://www.heavens-above.com/PassSkyChart2.ashx?passID=683230&size=800&lat=39.9042&lng=116.4074&loc=%e5%8c%97%e4%ba%ac%e5%b8%82&alt=52&tz=ChST&showUnlit=true","scoreData":[18,null,-15.9,16],"exist":124,"score":0,"id":"b51af85cd08a7b315cc44df2c99e7506"},{"url":"https://www.heavens-above.com/passdetails.aspx?lat=39.9042&lng=116.4074&loc=%e5%8c%97%e4%ba%ac%e5%b8%82&alt=52&tz=ChST&satid=25544&mjd=61067.48256107&type=A","date":"1月27日","brightness":"-2.1","events":{"rise":{"time":"19:30:48","altitude":"0°","azimuth":"306° (西北)","distance":"2,355","brightness":"0.8","sunAltitude":"-23.7°"},"reachAltitude10deg":{"time":"19:32:54","altitude":"10°","azimuth":"304° (西北)","distance":"1,490","brightness":"-0.3","sunAltitude":"-24.1°"},"enterShadow":{"time":"19:34:53","altitude":"33°","azimuth":"297° (西北偏西)","distance":"725","brightness":"-2.1","sunAltitude":"-24.5°"},"highestPoint":{"time":"19:36:14","altitude":"72°","azimuth":"219° (西南)","distance":"439","brightness":"-","sunAltitude":"-24.7°"},"dropBelowAltitude10deg":{"time":"19:39:33","altitude":"10°","azimuth":"135° (东南)","distance":"1,484","brightness":"-","sunAltitude":"-25.4°"},"set":{"time":"19:41:38","altitude":"0°","azimuth":"133° (东南)","distance":"2,344","brightness":"-","sunAltitude":"-25.8°"}},"passType":"可见","image":"https://www.heavens-above.com/PassSkyChart2.ashx?passID=683231&size=800&lat=39.9042&lng=116.4074&loc=%e5%8c%97%e4%ba%ac%e5%b8%82&alt=52&tz=ChST&showUnlit=true","scoreData":[19,null,-24.7,72],"exist":119,"score":0,"id":"8645943bc5bf5a6c5c8656bc76101bea"},{"url":"https://www.heavens-above.com/passdetails.aspx?lat=39.9042&lng=116.4074&loc=%e5%8c%97%e4%ba%ac%e5%b8%82&alt=52&tz=ChST&satid=25544&mjd=61053.477440851&type=A","date":"1月13日","brightness":"-1.6","events":{"rise":{"time":"19:23:17","altitude":"0°","azimuth":"258° (西南偏西)","distance":"2,345","brightness":"1.4","sunAltitude":"-24.8°"},"reachAltitude10deg":{"time":"19:25:33","altitude":"10°","azimuth":"270° (西)","distance":"1,486","brightness":"0.1","sunAltitude":"-25.3°"},"enterShadow":{"time":"19:27:30","altitude":"24°","azimuth":"301° (西北偏西)","distance":"907","brightness":"-1.6","sunAltitude":"-25.6°"},"highestPoint":{"time":"19:28:30","altitude":"29°","azimuth":"333° (西北偏北)","distance":"803","brightness":"-","sunAltitude":"-25.8°"},"dropBelowAltitude10deg":{"time":"19:31:29","altitude":"10°","azimuth":"35° (东北)","distance":"1,495","brightness":"-","sunAltitude":"-26.4°"},"set":{"time":"19:33:46","altitude":"0°","azimuth":"47° (东北)","distance":"2,362","brightness":"-","sunAltitude":"-26.8°"}},"passType":"可见","image":"https://www.heavens-above.com/PassSkyChart2.ashx?passID=683185&size=800&lat=39.9042&lng=116.4074&loc=%e5%8c%97%e4%ba%ac%e5%b8%82&alt=52&tz=ChST&showUnlit=true","scoreData":[19,null,-25.8,29],"exist":117,"score":0,"id":"3d1b1638ff7c0209d41e71ddaa28bd7f"},{"url":"https://www.heavens-above.com/passdetails.aspx?lat=39.9042&lng=116.4074&loc=%e5%8c%97%e4%ba%ac%e5%b8%82&alt=52&tz=ChST&satid=25544&mjd=61051.4761422319&type=A","date":"1月11日","brightness":"-1.8","events":{"rise":{"time":"19:21:45","altitude":"0°","azimuth":"236° (西南偏西)","distance":"2,340","brightness":"1.1","sunAltitude":"-24.9°"},"reachAltitude10deg":{"time":"19:23:50","altitude":"10°","azimuth":"239° (西南偏西)","distance":"1,482","brightness":"-0.1","sunAltitude":"-25.3°"},"enterShadow":{"time":"19:25:38","altitude":"29°","azimuth":"246° (西南偏西)","distance":"783","brightness":"-1.8","sunAltitude":"-25.6°"},"highestPoint":{"time":"19:27:09","altitude":"71°","azimuth":"324° (西北)","distance":"443","brightness":"-","sunAltitude":"-25.9°"},"dropBelowAltitude10deg":{"time":"19:30:29","altitude":"10°","azimuth":"49° (东北)","distance":"1,494","brightness":"-","sunAltitude":"-26.5°"},"set":{"time":"19:32:36","altitude":"0°","azimuth":"52° (东北)","distance":"2,362","brightness":"-","sunAltitude":"-26.9°"}},"passType":"可见","image":"https://www.heavens-above.com/PassSkyChart2.ashx?passID=683178&size=800&lat=39.9042&lng=116.4074&loc=%e5%8c%97%e4%ba%ac%e5%b8%82&alt=52&tz=ChST&showUnlit=true","scoreData":[19,null,-25.9,71],"exist":108,"score":0,"id":"64524ddd9c91987cfc75a397d8fcaa57"},{"url":"https://www.heavens-above.com/passdetails.aspx?lat=39.9042&lng=116.4074&loc=%e5%8c%97%e4%ba%ac%e5%b8%82&alt=52&tz=ChST&satid=25544&mjd=61088.8752135727&type=A","date":"2月18日","brightness":"-1.7","events":{"rise":{"time":"04:53:12","altitude":"0°","azimuth":"246° (西南偏西)","distance":"2,343","brightness":"-","sunAltitude":"-25.7°"},"reachAltitude10deg":{"time":"04:55:20","altitude":"10°","azimuth":"252° (西南偏西)","distance":"1,483","brightness":"-","sunAltitude":"-25.3°"},"highestPoint":{"time":"04:58:33","altitude":"46°","azimuth":"327° (西北偏北)","distance":"568","brightness":"-","sunAltitude":"-24.7°"},"exitShadow":{"time":"05:00:18","altitude":"23°","azimuth":"31° (东北偏北)","distance":"935","brightness":"-1.7","sunAltitude":"-24.3°"},"dropBelowAltitude10deg":{"time":"05:01:48","altitude":"10°","azimuth":"43° (东北)","distance":"1,490","brightness":"-0.4","sunAltitude":"-24.0°"},"set":{"time":"05:03:57","altitude":"0°","azimuth":"49° (东北)","distance":"2,355","brightness":"0.9","sunAltitude":"-23.6°"}},"passType":"可见","image":"https://www.heavens-above.com/PassSkyChart2.ashx?passID=683264&size=800&lat=39.9042&lng=116.4074&loc=%e5%8c%97%e4%ba%ac%e5%b8%82&alt=52&tz=ChST&showUnlit=true","scoreData":[4,null,-24.7,46],"exist":90,"score":0,"id":"7ef98e3bf8da6d7eaae5531271610082"},{"url":"https://www.heavens-above.com/passdetails.aspx?lat=39.9042&lng=116.4074&loc=%e5%8c%97%e4%ba%ac%e5%b8%82&alt=52&tz=ChST&satid=25544&mjd=61055.478472362&type=A","date":"1月15日","brightness":"-1.1","events":{"rise":{"time":"19:25:04","altitude":"0°","azimuth":"278° (西)","distance":"2,349","brightness":"1.3","sunAltitude":"-24.8°"},"reachAltitude10deg":{"time":"19:27:43","altitude":"10°","azimuth":"300° (西北偏西)","distance":"1,490","brightness":"-0.3","sunAltitude":"-25.3°"},"enterShadow":{"time":"19:28:59","altitude":"15°","azimuth":"321° (西北)","distance":"1,226","brightness":"-1.1","sunAltitude":"-25.6°"},"highestPoint":{"time":"19:29:56","altitude":"17°","azimuth":"342° (西北偏北)","distance":"1,159","brightness":"-","sunAltitude":"-25.7°"},"dropBelowAltitude10deg":{"time":"19:32:11","altitude":"10°","azimuth":"24° (东北偏北)","distance":"1,495","brightness":"-","sunAltitude":"-26.2°"},"set":{"time":"19:34:51","altitude":"0°","azimuth":"47° (东北)","distance":"2,362","brightness":"-","sunAltitude":"-26.7°"}},"passType":"可见","image":"https://www.heavens-above.com/PassSkyChart2.ashx?passID=683193&size=800&lat=39.9042&lng=116.4074&loc=%e5%8c%97%e4%ba%ac%e5%b8%82&alt=52&tz=ChST&showUnlit=true","scoreData":[19,null,-25.7,17],"exist":76,"score":0,"id":"b0a2e756fbfca1d857bab97488b1c7d6"},{"url":"https://www.heavens-above.com/passdetails.aspx?lat=39.9042&lng=116.4074&loc=%e5%8c%97%e4%ba%ac%e5%b8%82&alt=52&tz=ChST&satid=25544&mjd=61090.8745624307&type=A","date":"2月20日","brightness":"-1.2","events":{"rise":{"time":"04:52:33","altitude":"0°","azimuth":"266° (西)","distance":"2,347","brightness":"-","sunAltitude":"-25.3°"},"reachAltitude10deg":{"time":"04:54:56","altitude":"10°","azimuth":"282° (西北偏西)","distance":"1,486","brightness":"-","sunAltitude":"-24.9°"},"highestPoint":{"time":"04:57:39","altitude":"23°","azimuth":"336° (西北偏北)","distance":"947","brightness":"-","sunAltitude":"-24.4°"},"exitShadow":{"time":"04:59:22","altitude":"16°","azimuth":"17° (东北偏北)","distance":"1,193","brightness":"-1.2","sunAltitude":"-24.0°"},"dropBelowAltitude10deg":{"time":"05:00:22","altitude":"10°","azimuth":"31° (东北偏北)","distance":"1,490","brightness":"-0.5","sunAltitude":"-23.8°"},"set":{"time":"05:02:46","altitude":"0°","azimuth":"46° (东北)","distance":"2,355","brightness":"0.8","sunAltitude":"-23.4°"}},"passType":"可见","image":"https://www.heavens-above.com/PassSkyChart2.ashx?passID=683278&size=800&lat=39.9042&lng=116.4074&loc=%e5%8c%97%e4%ba%ac%e5%b8%82&alt=52&tz=ChST&showUnlit=true","scoreData":[4,null,-24.4,23],"exist":60,"score":0,"id":"2e4681c05de156b009062d8229a7035c"},{"url":"https://www.heavens-above.com/passdetails.aspx?lat=39.9042&lng=116.4074&loc=%e5%8c%97%e4%ba%ac%e5%b8%82&alt=52&tz=ChST&satid=25544&mjd=61065.4816985189&type=A","date":"1月25日","brightness":"-1.3","events":{"rise":{"time":"19:30:29","altitude":"0°","azimuth":"311° (西北)","distance":"2,356","brightness":"0.7","sunAltitude":"-24.0°"},"reachAltitude10deg":{"time":"19:32:40","altitude":"10°","azimuth":"319° (西北)","distance":"1,491","brightness":"-0.5","sunAltitude":"-24.4°"},"enterShadow":{"time":"19:33:38","altitude":"17°","azimuth":"327° (西北偏北)","distance":"1,129","brightness":"-1.3","sunAltitude":"-24.6°"},"highestPoint":{"time":"19:35:51","altitude":"41°","azimuth":"31° (东北偏北)","distance":"621","brightness":"-","sunAltitude":"-25.0°"},"dropBelowAltitude10deg":{"time":"19:39:02","altitude":"10°","azimuth":"103° (东南偏东)","distance":"1,488","brightness":"-","sunAltitude":"-25.7°"},"set":{"time":"19:41:12","altitude":"0°","azimuth":"111° (东南偏东)","distance":"2,349","brightness":"-","sunAltitude":"-26.1°"}},"passType":"可见","image":"https://www.heavens-above.com/PassSkyChart2.ashx?passID=683215&size=800&lat=39.9042&lng=116.4074&loc=%e5%8c%97%e4%ba%ac%e5%b8%82&alt=52&tz=ChST&showUnlit=true","scoreData":[19,null,-25,41],"exist":58,"score":0,"id":"404bea9a16f9ad9c5bffb1cadce15e86"},{"url":"https://www.heavens-above.com/passdetails.aspx?lat=39.9042&lng=116.4074&loc=%e5%8c%97%e4%ba%ac%e5%b8%82&alt=52&tz=ChST&satid=25544&mjd=61043.8801161672&type=A","date":"1月4日","brightness":"-0.9","events":{"rise":{"time":"04:59:11","altitude":"0°","azimuth":"304° (西北)","distance":"2,376","brightness":"-","sunAltitude":"-29.3°"},"reachAltitude10deg":{"time":"05:01:18","altitude":"10°","azimuth":"301° (西北偏西)","distance":"1,510","brightness":"-","sunAltitude":"-28.9°"},"highestPoint":{"time":"05:04:39","altitude":"60°","azimuth":"221° (西南)","distance":"488","brightness":"-","sunAltitude":"-28.3°"},"exitShadow":{"time":"05:07:22","altitude":"15°","azimuth":"143° (东南)","distance":"1,257","brightness":"-0.9","sunAltitude":"-27.8°"},"dropBelowAltitude10deg":{"time":"05:07:59","altitude":"10°","azimuth":"141° (东南)","distance":"1,503","brightness":"-0.4","sunAltitude":"-27.6°"},"set":{"time":"05:10:05","altitude":"0°","azimuth":"137° (东南)","distance":"2,365","brightness":"0.8","sunAltitude":"-27.2°"}},"passType":"可见","image":"https://www.heavens-above.com/PassSkyChart2.ashx?passID=683179&size=800&lat=39.9042&lng=116.4074&loc=%e5%8c%97%e4%ba%ac%e5%b8%82&alt=52&tz=ChST&showUnlit=true","scoreData":[5,null,-28.3,60],"exist":37,"score":0,"id":"a3d7b328f811a165f38a701b68fc65f8"},{"url":"https://www.heavens-above.com/passdetails.aspx?lat=39.9042&lng=116.4074&loc=%e5%8c%97%e4%ba%ac%e5%b8%82&alt=52&tz=ChST&satid=25544&mjd=61049.4745451746&type=A","date":"1月9日","brightness":"-1.0","events":{"rise":{"time":"19:20:39","altitude":"0°","azimuth":"213° (西南偏南)","distance":"2,337","brightness":"0.6","sunAltitude":"-25.0°"},"reachAltitude10deg":{"time":"19:22:48","altitude":"10°","azimuth":"204° (西南偏南)","distance":"1,480","brightness":"-0.6","sunAltitude":"-25.4°"},"enterShadow":{"time":"19:23:20","altitude":"14°","azimuth":"200° (西南偏南)","distance":"1,284","brightness":"-1.0","sunAltitude":"-25.5°"},"highestPoint":{"time":"19:25:53","altitude":"36°","azimuth":"136° (东南)","distance":"671","brightness":"-","sunAltitude":"-26.0°"},"dropBelowAltitude10deg":{"time":"19:29:00","altitude":"10°","azimuth":"68° (东北偏东)","distance":"1,493","brightness":"-","sunAltitude":"-26.6°"},"set":{"time":"19:31:12","altitude":"0°","azimuth":"59° (东北偏东)","distance":"2,361","brightness":"-","sunAltitude":"-27.0°"}},"passType":"可见","image":"https://www.heavens-above.com/PassSkyChart2.ashx?passID=683175&size=800&lat=39.9042&lng=116.4074&loc=%e5%8c%97%e4%ba%ac%e5%b8%82&alt=52&tz=ChST&showUnlit=true","scoreData":[19,null,-26,36],"exist":32,"score":0,"id":"01fdc5e3c674b07c34b29deae16b49fa"},{"url":"https://www.heavens-above.com/passdetails.aspx?lat=39.9042&lng=116.4074&loc=%e5%8c%97%e4%ba%ac%e5%b8%82&alt=52&tz=ChST&satid=25544&mjd=61063.48105932&type=A","date":"1月23日","brightness":"-0.8","events":{"rise":{"time":"19:30:04","altitude":"0°","azimuth":"314° (西北)","distance":"2,356","brightness":"0.6","sunAltitude":"-24.3°"},"reachAltitude10deg":{"time":"19:32:32","altitude":"10°","azimuth":"331° (西北偏北)","distance":"1,492","brightness":"-0.7","sunAltitude":"-24.8°"},"enterShadow":{"time":"19:32:43","altitude":"11°","azimuth":"333° (西北偏北)","distance":"1,434","brightness":"-0.8","sunAltitude":"-24.8°"},"highestPoint":{"time":"19:35:08","altitude":"21°","azimuth":"22° (东北偏北)","distance":"1,009","brightness":"-","sunAltitude":"-25.3°"},"dropBelowAltitude10deg":{"time":"19:37:44","altitude":"10°","azimuth":"73° (东北偏东)","distance":"1,491","brightness":"-","sunAltitude":"-25.8°"},"set":{"time":"19:40:11","altitude":"0°","azimuth":"91° (东)","distance":"2,353","brightness":"-","sunAltitude":"-26.3°"}},"passType":"可见","image":"https://www.heavens-above.com/PassSkyChart2.ashx?passID=683237&size=800&lat=39.9042&lng=116.4074&loc=%e5%8c%97%e4%ba%ac%e5%b8%82&alt=52&tz=ChST&showUnlit=true","scoreData":[19,null,-25.3,21],"exist":11,"score":0,"id":"fd0ebc877c165d704aaf0f4bcfd25ec6"},{"url":"https://www.heavens-above.com/passdetails.aspx?lat=39.9042&lng=116.4074&loc=%e5%8c%97%e4%ba%ac%e5%b8%82&alt=52&tz=ChST&satid=25544&mjd=61057.4792845022&type=A","date":"1月17日","brightness":"-0.7","events":{"rise":{"time":"19:26:50","altitude":"0°","azimuth":"294° (西北偏西)","distance":"2,353","brightness":"1.0","sunAltitude":"-24.8°"},"reachAltitude10deg":{"time":"19:30:01","altitude":"10°","azimuth":"328° (西北偏北)","distance":"1,493","brightness":"-0.7","sunAltitude":"-25.4°"},"enterShadow":{"time":"19:30:10","altitude":"10°","azimuth":"330° (西北偏北)","distance":"1,471","brightness":"-0.7","sunAltitude":"-25.4°"},"highestPoint":{"time":"19:31:25","altitude":"12°","azimuth":"352° (北)","distance":"1,375","brightness":"-","sunAltitude":"-25.7°"},"dropBelowAltitude10deg":{"time":"19:32:49","altitude":"10°","azimuth":"17° (东北偏北)","distance":"1,495","brightness":"-","sunAltitude":"-25.9°"},"set":{"time":"19:36:01","altitude":"0°","azimuth":"50° (东北)","distance":"2,361","brightness":"-","sunAltitude":"-26.6°"}},"passType":"可见","image":"https://www.heavens-above.com/PassSkyChart2.ashx?passID=683199&size=800&lat=39.9042&lng=116.4074&loc=%e5%8c%97%e4%ba%ac%e5%b8%82&alt=52&tz=ChST&showUnlit=true","scoreData":[19,null,-25.7,12],"exist":9,"score":0,"id":"b343f711fa39344b48a97076963c29d9"}]